mcp_openwebui_demo/__init__.py
mcp_openwebui_demo/__main__.py
mcp_openwebui_demo/exampple-server-http.py
mcp_openwebui_demo/functions.py
mcp_openwebui_demo/mcp_main.py
mcp_openwebui_demo-0.0.7.dist-info/METADATA
mcp_openwebui_demo-0.0.7.dist-info/WHEEL
mcp_openwebui_demo-0.0.7.dist-info/entry_points.txt
mcp_openwebui_demo-0.0.7.dist-info/top_level.txt
mcp_openwebui_demo-0.0.7.dist-info/RECORD
