Metadata-Version: 2.4
Name: mcp-openwebui-demo
Version: 0.0.7
Summary: Add your description here
Author-email: JungJungIn <call518@gmail.com>
Requires-Python: >=3.12
Requires-Dist: fastmcp>=2.11.1
Provides-Extra: dev
Requires-Dist: pytest>=7.0.0; extra == "dev"
Requires-Dist: pytest-asyncio>=0.21.0; extra == "dev"
